hydrotools/metrics/__init__.py
hydrotools/metrics/_validation.py
hydrotools/metrics/_version.py
hydrotools/metrics/events.py
hydrotools/metrics/flow_duration_curve.py
hydrotools/metrics/metrics.py
hydrotools_metrics-2.2.0.dist-info/licenses/LICENSE
hydrotools_metrics-2.2.0.dist-info/licenses/NOTICE
hydrotools_metrics-2.2.0.dist-info/METADATA
hydrotools_metrics-2.2.0.dist-info/WHEEL
hydrotools_metrics-2.2.0.dist-info/top_level.txt
hydrotools_metrics-2.2.0.dist-info/RECORD
