Metadata-Version: 2.4
Name: hydrotools.metrics
Version: 2.2.0
Summary: Variety of standard model evaluation metrics.
Author-email: "Jason A. Regina" <jason.regina@noaa.gov>
License: 
Project-URL: Homepage, https://github.com/NOAA-OWP/hydrotools
Project-URL: Documentation, https://noaa-owp.github.io/hydrotools/hydrotools.metrics.html
Project-URL: Repository, https://github.com/NOAA-OWP/hydrotools/tree/main/python/metrics
Project-URL: Bug Tracker, https://github.com/NOAA-OWP/hydrotools/issues
Classifier: Development Status :: 4 - Beta
Classifier: Intended Audience :: Education
Classifier: Intended Audience :: Science/Research
Classifier: License :: OSI Approved :: Apache Software License
Classifier: Programming Language :: Python :: 3.10
Classifier: Programming Language :: Python :: 3.11
Classifier: Programming Language :: Python :: 3.12
Classifier: Topic :: Scientific/Engineering :: Hydrology
Classifier: Operating System :: OS Independent
Requires-Python: >=3.10
License-File: LICENSE
License-File: NOTICE
Requires-Dist: numpy>=1.20.0
Requires-Dist: pandas
Requires-Dist: scipy
Requires-Dist: arch
Provides-Extra: develop
Requires-Dist: pytest; extra == "develop"
Dynamic: license-file
